<?xml version="1.0" encoding="utf-8" ?>
<dwsync>
<file name="image_1.jpg" server="C:/wamp/www/THI_sandbox/" local="129281871039882816" remote="129281871030000000" />
<file name="image_10.jpg" server="C:/wamp/www/THI_sandbox/" local="129281869207734368" remote="129281869200000000" />
<file name="image_11.jpg" server="C:/wamp/www/THI_sandbox/" local="129281868984765632" remote="129281868980000000" />
<file name="image_12.jpg" server="C:/wamp/www/THI_sandbox/" local="129281868792304688" remote="129281868790000000" />
<file name="image_13.jpg" server="C:/wamp/www/THI_sandbox/" local="129281868598632816" remote="129281868590000000" />
<file name="image_14.jpg" server="C:/wamp/www/THI_sandbox/" local="129281868367773440" remote="129281868360000000" />
<file name="image_15.jpg" server="C:/wamp/www/THI_sandbox/" local="129281868110859376" remote="129281868110000000" />
<file name="image_16.jpg" server="C:/wamp/www/THI_sandbox/" local="129281867843984384" remote="129281867840000000" />
<file name="image_17.jpg" server="C:/wamp/www/THI_sandbox/" local="129281871909218752" remote="129281871900000000" />
<file name="image_18.jpg" server="C:/wamp/www/THI_sandbox/" local="129281871708359376" remote="129281871700000000" />
<file name="image_19.jpg" server="C:/wamp/www/THI_sandbox/" local="129281871499882816" remote="129281871490000000" />
<file name="image_2.jpg" server="C:/wamp/www/THI_sandbox/" local="129281870841562496" remote="129281870840000000" />
<file name="image_20.jpg" server="C:/wamp/www/THI_sandbox/" local="129281871271015616" remote="129281871270000000" />
<file name="image_3.jpg" server="C:/wamp/www/THI_sandbox/" local="129281870623984384" remote="129281870620000000" />
<file name="image_4.jpg" server="C:/wamp/www/THI_sandbox/" local="129281870454257808" remote="129281870450000000" />
<file name="image_5.jpg" server="C:/wamp/www/THI_sandbox/" local="129281870277500000" remote="129281870270000000" />
<file name="image_6.jpg" server="C:/wamp/www/THI_sandbox/" local="129281870044140624" remote="129281870040000000" />
<file name="image_7.jpg" server="C:/wamp/www/THI_sandbox/" local="129281869843945312" remote="129281869840000000" />
<file name="image_8.jpg" server="C:/wamp/www/THI_sandbox/" local="129281869630273440" remote="129281869630000000" />
<file name="image_9.jpg" server="C:/wamp/www/THI_sandbox/" local="129281869439453120" remote="129281869430000000" />
</dwsync>